{"cameraMode":{"drawMode":0,"name":"Shaded","section":"Shading Mode"},"sceneLighting":true,"audioPlay":false,"sceneViewState":{"m_AlwaysRefresh":false,"showFog":true,"showSkybox":true,"showFlares":true,"showImageEffects":true,"showParticleSystems":true,"showVisualEffectGraphs":true,"m_FxEnabled":true},"in2DMode":false,"pivot":{"x":445.0116271972656,"y":195.33294677734376,"z":0.171875},"rotation":{"x":0.007499924395233393,"y":0.001499961013905704,"z":-0.000011251605428697076,"w":0.9999694228172302},"size":304.4056701660156,"orthographic":false}